inuits_policy_based_auth/__init__.py
inuits_policy_based_auth/exceptions.py
inuits_policy_based_auth/policy_factory.py
inuits_policy_based_auth/authentication/__init__.py
inuits_policy_based_auth/authentication/base_authentication_policy.py
inuits_policy_based_auth/authentication/policies/__init__.py
inuits_policy_based_auth/authentication/policies/token_based_policies/__init__.py
inuits_policy_based_auth/authentication/policies/token_based_policies/authlib_flask_oauth2_policy.py
inuits_policy_based_auth/authentication/policies/token_based_policies/tenant_token_roles_policy.py
inuits_policy_based_auth/authorization/__init__.py
inuits_policy_based_auth/authorization/base_authorization_policy.py
inuits_policy_based_auth/authorization/policies/__init__.py
inuits_policy_based_auth/authorization/policies/open_data_policy.py
inuits_policy_based_auth/authorization/policies/scope_based_policy.py
inuits_policy_based_auth/authorization/policies/super_admin_policy.py
inuits_policy_based_auth/contexts/__init__.py
inuits_policy_based_auth/contexts/policy_context.py
inuits_policy_based_auth/contexts/request_context.py
inuits_policy_based_auth/contexts/user_context.py
inuits_policy_based_auth/helpers/__init__.py
inuits_policy_based_auth/helpers/access_restrictions.py
inuits_policy_based_auth/helpers/immutable_dict.py
inuits_policy_based_auth/helpers/tenant.py
tests/__init__.py
tests/integration/__init__.py
tests/integration/custom_token.py
tests/integration/flask_process.py
tests/integration/helpers.py
tests/integration/test_policy_factory.py
tests/integration/authentication/__init__.py
tests/integration/authentication/test_authlib_flask_oauth2_policy.py
tests/integration/authentication/test_tenant_token_roles_policy.py
tests/integration/authorization/__init__.py
tests/integration/authorization/test_open_data_policy.py
tests/integration/authorization/test_scope_based_policy.py
tests/integration/authorization/test_super_admin_policy.py
tests/integration/test_api/__init__.py
inuits_policy_based_auth-10.0.1.dist-info/LICENSE
inuits_policy_based_auth-10.0.1.dist-info/METADATA
inuits_policy_based_auth-10.0.1.dist-info/WHEEL
inuits_policy_based_auth-10.0.1.dist-info/top_level.txt
inuits_policy_based_auth-10.0.1.dist-info/RECORD
