Metadata-Version: 2.1
Name: inuits_policy_based_auth
Version: 10.0.1
Summary: Module for securing API endpoints based on policies.
Author-email: Inuits <developers@inuits.eu>
License:                     GNU GENERAL PUBLIC LICENSE
Project-URL: Homepage, https://github.com/inuits/inuits-policy-based-auth
Keywords: inuits,policy,auth
Classifier: License :: OSI Approved :: GNU General Public License v2 (GPLv2)
Classifier: Intended Audience :: Developers
Classifier: Programming Language :: Python :: 3
Classifier: Programming Language :: Python :: 3.8
Classifier: Programming Language :: Python :: 3.9
Classifier: Programming Language :: Python :: 3.10
Classifier: Programming Language :: Python :: 3.11
License-File: LICENSE
Requires-Dist: Authlib>=1.2.1
Requires-Dist: requests>=2.31
Requires-Dist: Werkzeug>=2
Provides-Extra: dev
Requires-Dist: coverage>=7; extra == "dev"
Requires-Dist: Flask-RESTful>=0.3.10; extra == "dev"
Requires-Dist: Flask>=3; extra == "dev"
Requires-Dist: pyjwt>=2.8; extra == "dev"
Requires-Dist: pytest>=7; extra == "dev"
Requires-Dist: python-dotenv>=1; extra == "dev"
